aieng_bot_maintain/__init__.py
aieng_bot_maintain/cli.py
aieng_bot_maintain/_cli/__init__.py
aieng_bot_maintain/_cli/utils.py
aieng_bot_maintain/_cli/commands/__init__.py
aieng_bot_maintain/_cli/commands/apply_fix.py
aieng_bot_maintain/_cli/commands/classify.py
aieng_bot_maintain/_cli/commands/collect_metrics.py
aieng_bot_maintain/_cli/commands/process_queue.py
aieng_bot_maintain/agent_fixer/__init__.py
aieng_bot_maintain/agent_fixer/fixer.py
aieng_bot_maintain/agent_fixer/models.py
aieng_bot_maintain/agent_fixer/prompts.py
aieng_bot_maintain/auto_merger/__init__.py
aieng_bot_maintain/auto_merger/activity_logger.py
aieng_bot_maintain/auto_merger/models.py
aieng_bot_maintain/auto_merger/pr_processor.py
aieng_bot_maintain/auto_merger/queue_manager.py
aieng_bot_maintain/auto_merger/state_manager.py
aieng_bot_maintain/auto_merger/status_poller.py
aieng_bot_maintain/auto_merger/workflow_client.py
aieng_bot_maintain/classifier/__init__.py
aieng_bot_maintain/classifier/classifier.py
aieng_bot_maintain/classifier/models.py
aieng_bot_maintain/classifier/prompts.py
aieng_bot_maintain/metrics/__init__.py
aieng_bot_maintain/metrics/collector.py
aieng_bot_maintain/observability/__init__.py
aieng_bot_maintain/observability/classifiers.py
aieng_bot_maintain/observability/extractors.py
aieng_bot_maintain/observability/parsers.py
aieng_bot_maintain/observability/processors.py
aieng_bot_maintain/observability/storage.py
aieng_bot_maintain/observability/tracer.py
aieng_bot_maintain/utils/__init__.py
aieng_bot_maintain/utils/logging.py
aieng_bot_maintain-0.4.0.dist-info/METADATA
aieng_bot_maintain-0.4.0.dist-info/WHEEL
aieng_bot_maintain-0.4.0.dist-info/entry_points.txt
aieng_bot_maintain-0.4.0.dist-info/licenses/LICENSE.md
aieng_bot_maintain-0.4.0.dist-info/RECORD
