Metadata-Version: 2.4
Name: aieng-bot-maintain
Version: 0.4.0
Summary: Vector Institute AI Engineering Bot for Maintenance Tasks
Project-URL: Homepage, https://github.com/VectorInstitute/aieng-bot-maintain
Project-URL: Repository, https://github.com/VectorInstitute/aieng-bot-maintain
Project-URL: Issues, https://github.com/VectorInstitute/aieng-bot-maintain/issues
Project-URL: Changelog, https://github.com/VectorInstitute/aieng-bot-maintain/releases
Author-email: Vector AI Engineering <ai_engineering@vectorinstitute.ai>
License: Apache-2.0
License-File: LICENSE.md
Keywords: ai,automation,claude,dependabot,github,maintenance
Classifier: Development Status :: 4 - Beta
Classifier: Intended Audience :: Developers
Classifier: License :: OSI Approved :: Apache Software License
Classifier: Programming Language :: Python :: 3
Classifier: Programming Language :: Python :: 3.12
Classifier: Topic :: Software Development :: Quality Assurance
Classifier: Topic :: Software Development :: Version Control :: Git
Requires-Python: >=3.12
Requires-Dist: anthropic>=0.42.0
Requires-Dist: claude-agent-sdk
Requires-Dist: pyyaml>=6.0.2
Requires-Dist: rich>=13.0.0
